importlint.py
importlint-0.2.dist-info/LICENSE
importlint-0.2.dist-info/METADATA
importlint-0.2.dist-info/WHEEL
importlint-0.2.dist-info/entry_points.txt
importlint-0.2.dist-info/top_level.txt
importlint-0.2.dist-info/RECORD
