Metadata-Version: 2.1
Name: importlint
Version: 0.2
Summary: Check and fix your module and package imports in python files
Home-page: https://github.com/JakeRoggenbuck/ImportLinter
Author: Jake Roggenbuck
Author-email: jake@jr0.org
License: MIT
Platform: UNKNOWN
